coacoa/__init__.py
coacoa/__main__.py
coacoa/config.py
coacoa/scaffold/__init__.py
coacoa/scaffold/agents/analyst.md
coacoa/scaffold/agents/architect.md
coacoa/scaffold/agents/code_explorer.md
coacoa/scaffold/agents/dev.md
coacoa/scaffold/agents/orchestrator.md
coacoa/scaffold/agents/pm.md
coacoa/scaffold/agents/po.md
coacoa/scaffold/agents/qa.md
coacoa/scaffold/agents/scrum_master.md
coacoa/scaffold/agents/ux_designer.md
coacoa/scaffold/context/analysis.md
coacoa/scaffold/context/intelligence/complexity.json
coacoa/scaffold/context/intelligence/coverage.json
coacoa/scaffold/context/intelligence/dep_graph.json
coacoa/scaffold/context/intelligence/hotspots.json
coacoa/scaffold/context/intelligence/module_map.json
coacoa/scaffold/data/language_rules.md
coacoa/scaffold/data/solid_policy.md
coacoa/scaffold/data/tech_preferences.md
coacoa/scaffold/ide_helpers/claude.md
coacoa/scaffold/ide_helpers/.clinerules/coacoa_commands.md
coacoa/scaffold/quality/anti_hallucination.md
coacoa/scaffold/quality/architecture_integrity.md
coacoa/scaffold/quality/build_integrity.md
coacoa/scaffold/quality/link_integrity.md
coacoa/scaffold/quality/qa.md
coacoa/scaffold/tasks/analyze_codebase.md
coacoa/scaffold/tasks/generate_architecture.md
coacoa/scaffold/tasks/generate_prd.md
coacoa/scaffold/tasks/generate_stories.md
coacoa/scaffold/tasks/implement_story.md
coacoa/scaffold/tasks/manage_story_branch.md
coacoa/scaffold/tasks/qa_review_story.md
coacoa/scaffold/tasks/refine_epics.md
coacoa/scaffold/tasks/shard_doc.md
coacoa/scaffold/tasks/write_adr.md
coacoa/scaffold/templates/adr.md
coacoa/scaffold/templates/architecture.md
coacoa/scaffold/templates/epic.md
coacoa/scaffold/templates/prd.md
coacoa/scaffold/templates/story.md
coacoa/scaffold/templates/ui_ux.md
coacoa/scaffold/workflows/default_brownfield.yaml
coacoa/scaffold/workflows/default_greenfield.yaml
coacoa-0.1.0b2.post2.dist-info/licenses/LICENSE
coacoa-0.1.0b2.post2.dist-info/METADATA
coacoa-0.1.0b2.post2.dist-info/WHEEL
coacoa-0.1.0b2.post2.dist-info/entry_points.txt
coacoa-0.1.0b2.post2.dist-info/top_level.txt
coacoa-0.1.0b2.post2.dist-info/RECORD
